Aadhar-1.0.0.dist-info/METADATA
Aadhar-1.0.0.dist-info/RECORD
Aadhar-1.0.0.dist-info/WHEEL
Aadhar-1.0.0.dist-info/top_level.txt
aadhar/__init__.py
