Metadata-Version: 2.1
Name: Aadhar
Version: 1.0.0
Summary: Python Library to validate and generate aadhar numbers
Home-page: https://github.com/NikhilPanwar/
Author: Nikhil Panwar
Author-email: npanwar80@gmail.com
License: UNKNOWN
Platform: UNKNOWN
Classifier: Programming Language :: Python :: 3
Classifier: License :: OSI Approved :: MIT License
Classifier: Operating System :: OS Independent
